napari_voxtell/__init__.py
napari_voxtell/napari.yaml
napari_voxtell/widget_gui.py
napari_voxtell/widget_main.py
napari_voxtell-0.1.0.dist-info/licenses/LICENSE
napari_voxtell-0.1.0.dist-info/METADATA
napari_voxtell-0.1.0.dist-info/WHEEL
napari_voxtell-0.1.0.dist-info/entry_points.txt
napari_voxtell-0.1.0.dist-info/top_level.txt
napari_voxtell-0.1.0.dist-info/RECORD
