Metadata-Version: 2.4
Name: napari-voxtell
Version: 0.1.0
Summary: Voxtell - Text-promptable segmentation plugin for Napari
Author-email: Benjamin Hamm <benjamin.hamm@dkfz-heidelberg.de>, Maximilian Rokuss <maximilian.rokuss@dkfz-heidelberg.de>
License: 
Project-URL: Homepage, https://github.com/MIC-DKFZ/napari-voxtell
Project-URL: Code, https://github.com/MIC-DKFZ/napari-voxtell
Classifier: Development Status :: 2 - Pre-Alpha
Classifier: Framework :: napari
Classifier: Intended Audience :: Developers
Classifier: License :: OSI Approved :: Apache Software License
Classifier: Operating System :: OS Independent
Classifier: Programming Language :: Python
Classifier: Programming Language :: Python :: 3
Classifier: Programming Language :: Python :: 3 :: Only
Classifier: Programming Language :: Python :: 3.9
Classifier: Programming Language :: Python :: 3.10
Classifier: Programming Language :: Python :: 3.11
Classifier: Programming Language :: Python :: 3.12
Classifier: Topic :: Scientific/Engineering :: Image Processing
Requires-Python: >=3.10
License-File: LICENSE
Requires-Dist: numpy
Requires-Dist: qtpy
Requires-Dist: napari[all]
Requires-Dist: napari-nifti
Requires-Dist: voxtell
Provides-Extra: testing
Requires-Dist: tox; extra == "testing"
Requires-Dist: pytest; extra == "testing"
Requires-Dist: pytest-cov; extra == "testing"
Requires-Dist: pytest-qt; extra == "testing"
Requires-Dist: napari; extra == "testing"
Requires-Dist: pyqt5; extra == "testing"
Dynamic: license-file
